macros/__init__.py
macros/module_reader.py
macros/plugin.py
macros/test.py
useurmind_mkdocs_macros_plugin-0.2.2.dist-info/METADATA
useurmind_mkdocs_macros_plugin-0.2.2.dist-info/RECORD
useurmind_mkdocs_macros_plugin-0.2.2.dist-info/WHEEL
useurmind_mkdocs_macros_plugin-0.2.2.dist-info/entry_points.txt
useurmind_mkdocs_macros_plugin-0.2.2.dist-info/top_level.txt
