Metadata-Version: 2.1
Name: useurmind-mkdocs-macros-plugin
Version: 0.2.2
Summary: Unleash the power of MkDocs with macros and variables
Home-page: https://github.com/Useurmind/mkdocs_macros_plugin
Author: Laurent Franceschetti <info@settlenext.com>, Jochen Grün <jochen.gruen@googlemail.com>
Author-email: jochen.gruen@googlemail.com
License: MIT
Keywords: mkdocs python markdown macros
Platform: UNKNOWN
Classifier: Development Status :: 5 - Production/Stable
Classifier: Intended Audience :: Developers
Classifier: Intended Audience :: Information Technology
Classifier: License :: OSI Approved :: MIT License
Classifier: Programming Language :: Python
Classifier: Programming Language :: Python :: 3 :: Only
Classifier: Programming Language :: Python :: 3.7
Requires-Python: >=3.7
Requires-Dist: mkdocs (>=1.0.2)
Requires-Dist: repackage
Requires-Dist: jinja2
Requires-Dist: mkdocs
